abdesign/__init__.py
abdesign/program.py
abdesign/core/__init__.py
abdesign/core/anarciobject.py
abdesign/core/igobject.py
abdesign/core/multiindex.py
abdesign/data/__init__.py
abdesign/data/cdr_library.py
abdesign/data/protein_iupac.py
abdesign/humanization/__init__.py
abdesign/humanization/humanize.py
abdesign/io/__init__.py
abdesign/io/file_reader.py
abdesign/tests/__init__.py
abdesign/tests/igobject_test.py
abdesign/util/__init__.py
abdesign/util/annotation.py
abdesign-0.0.3.dist-info/LICENSE
abdesign-0.0.3.dist-info/METADATA
abdesign-0.0.3.dist-info/WHEEL
abdesign-0.0.3.dist-info/top_level.txt
abdesign-0.0.3.dist-info/RECORD
