Metadata-Version: 2.1
Name: abdesign
Version: 0.0.3
Summary: Antibody humanization framework
Home-page: https://github.com/SchubertLab/ABDesign
Author: Jannis Köckritz
Author-email: jannis.koeckritz@helmholtz-muenchen.de
License: UNKNOWN
Platform: UNKNOWN
Classifier: Programming Language :: Python :: 3
Classifier: License :: OSI Approved :: MIT License
Classifier: Operating System :: MacOS :: MacOS X
Classifier: Operating System :: Unix
Requires-Python: >=3.6
Requires-Dist: pandas (>=1.0.3)
Requires-Dist: biopython
